pupmapper/__init__.py
pupmapper/_version.py
pupmapper/genmap.py
pupmapper/run_bigtools.py
pupmapper/utils.py
pupmapper-0.1.0.dist-info/METADATA
pupmapper-0.1.0.dist-info/WHEEL
pupmapper-0.1.0.dist-info/entry_points.txt
pupmapper-0.1.0.dist-info/licenses/LICENSE
pupmapper-0.1.0.dist-info/RECORD
