Metadata-Version: 2.1
Name: pupmapper
Version: 0.1.0
Summary: Tool & python package for calculating genome wide pileup mappability
Project-URL: Homepage, https://github.com/maxgmarin/pupmapper
Author-email: Maximillian Marin <maximilliangmarin@gmail.com>
License-File: LICENSE
Requires-Python: >=3.8
Requires-Dist: bioframe>=0.7.2
Requires-Dist: numpy
Requires-Dist: pandas
Requires-Dist: tqdm
Provides-Extra: test
Requires-Dist: pytest; extra == 'test'
